<?xml version="1.0" encoding="UTF-8"?>
<site generator-info-name="WebGrab+Plus/w MDB &amp; REX Postprocess -- version V2.1.11.0 -- Jan van Straaten" site="tvarenasport.si">
  <channels>
    <channel update="i" site="tvarena.si" site_id="1" xmltv_id="A1">A1</channel>
    <channel update="i" site="tvarena.si" site_id="2" xmltv_id="A2">A2</channel>
    <channel update="i" site="tvarena.si" site_id="3" xmltv_id="A3">A3</channel>
    <channel update="i" site="tvarena.si" site_id="4" xmltv_id="A4">A4</channel>
  </channels>
</site>